LICENSE.txt
README.md
setup.cfg
setup.py
sdc_orchestration_helpers/__init__.py
sdc_orchestration_helpers.egg-info/PKG-INFO
sdc_orchestration_helpers.egg-info/SOURCES.txt
sdc_orchestration_helpers.egg-info/dependency_links.txt
sdc_orchestration_helpers.egg-info/requires.txt
sdc_orchestration_helpers.egg-info/top_level.txt
sdc_orchestration_helpers/airflow/__init__.py
sdc_orchestration_helpers/airflow/airflow1/__init__.py
sdc_orchestration_helpers/airflow/airflow1/aws/__init__.py
sdc_orchestration_helpers/airflow/airflow1/aws/operators/__init__.py
sdc_orchestration_helpers/airflow/airflow1/aws/operators/athena.py
sdc_orchestration_helpers/airflow/airflow1/aws/operators/cloudwatch.py
sdc_orchestration_helpers/airflow/airflow1/aws/operators/ecs.py
sdc_orchestration_helpers/airflow/airflow1/aws/operators/glue.py
sdc_orchestration_helpers/airflow/airflow1/aws/operators/s3.py
sdc_orchestration_helpers/airflow/airflow1/aws/operators/sagemaker.py
sdc_orchestration_helpers/airflow/airflow1/aws/operators/terraform.py
sdc_orchestration_helpers/airflow/airflow1/aws/sensors/__init__.py
sdc_orchestration_helpers/airflow/airflow1/aws/sensors/athena.py
sdc_orchestration_helpers/airflow/airflow1/aws/sensors/cloudwatch.py
sdc_orchestration_helpers/airflow/airflow1/aws/sensors/ecs.py
sdc_orchestration_helpers/airflow/airflow1/aws/sensors/glue.py
sdc_orchestration_helpers/airflow/airflow1/aws/sensors/sagemaker.py
sdc_orchestration_helpers/airflow/airflow1/dagfactory/__init__.py
sdc_orchestration_helpers/airflow/airflow1/dagfactory/ecs/__init__.py
sdc_orchestration_helpers/airflow/airflow1/dagfactory/ecs/task_loaders.py
sdc_orchestration_helpers/airflow/airflow2/__init__.py
sdc_orchestration_helpers/airflow/airflow2/aws/__init__.py
sdc_orchestration_helpers/airflow/airflow2/aws/operators/__init__.py
sdc_orchestration_helpers/airflow/airflow2/aws/operators/cloudwatch.py
sdc_orchestration_helpers/airflow/airflow2/aws/operators/ecs.py
sdc_orchestration_helpers/airflow/airflow2/aws/operators/glue.py
sdc_orchestration_helpers/airflow/airflow2/aws/operators/s3.py
sdc_orchestration_helpers/airflow/airflow2/aws/sensors/__init__.py
sdc_orchestration_helpers/airflow/airflow2/aws/sensors/cloudwatch.py
