Metadata-Version: 2.1
Name: sdc-orchestration-helpers
Version: 0.4.5
Summary: A package of orchestration helpers and utilities for sdc orchestration i.e AIRFLOW.
Home-page: https://github.com/RingierIMU/sdc-global-orchestration-helpers
Author: Ringier South Africa
Author-email: tools@ringier.co.za
License: UNKNOWN
Download-URL: https://github.com/RingierIMU/sdc-global-orchestration-helpers/archive/v0.4.5.zip
Keywords: pip,helpers,airflow,orchestration
Platform: UNKNOWN
Provides-Extra: airflow1
Provides-Extra: airflow2
